Cubane-1.0.11.data/scripts/cubane
Cubane-1.0.11.dist-info/METADATA
Cubane-1.0.11.dist-info/RECORD
Cubane-1.0.11.dist-info/WHEEL
Cubane-1.0.11.dist-info/top_level.txt
cubane/__init__.py
cubane/backends.py
cubane/context_processors.py
cubane/decorators.py
cubane/default_views.py
cubane/forms.py
cubane/middleware.py
cubane/serializers.py
cubane/test_cubane.py
cubane/urls.py
cubane/views.py
cubane/aggregator/__init__.py
cubane/aggregator/source_base.py
cubane/aggregator/sources/__init__.py
cubane/aggregator/sources/aggregator.py
cubane/aggregator/sources/filter.py
cubane/aggregator/sources/twitter.py
cubane/aggregator/tests/__init__.py
cubane/aggregator/tests/aggregator.py
cubane/aggregator/tests/filter.py
cubane/aggregator/tests/source_base.py
cubane/aggregator/tests/twitter.py
cubane/backend/__init__.py
cubane/backend/api.py
cubane/backend/changelog.py
cubane/backend/dashboard.py
cubane/backend/forms.py
cubane/backend/middleware.py
cubane/backend/models.py
cubane/backend/urls.py
cubane/backend/views.py
cubane/backend/accounts/__init__.py
cubane/backend/accounts/forms.py
cubane/backend/accounts/models.py
cubane/backend/accounts/views.py
cubane/backend/accounts/templates/cubane/backend/accounts/change_password.html
cubane/backend/accounts/templates/cubane/backend/accounts/create_edit.html
cubane/backend/accounts/templates/cubane/backend/accounts/duplicate.html
cubane/backend/accounts/templates/cubane/backend/accounts/index.html
cubane/backend/accounts/templates/cubane/backend/groups/create_edit.html
cubane/backend/accounts/templates/cubane/backend/groups/duplicate.html
cubane/backend/accounts/templates/cubane/backend/groups/index.html
cubane/backend/accounts/templates/cubane/backend/permissions/create_edit.html
cubane/backend/accounts/templates/cubane/backend/permissions/duplicate.html
cubane/backend/accounts/templates/cubane/backend/permissions/index.html
cubane/backend/accounts/tests/__init__.py
cubane/backend/accounts/tests/forms.py
cubane/backend/accounts/tests/views.py
cubane/backend/static/cubane/backend/bootstrap/css/bootstrap-fixes.css
