Metadata-Version: 2.1
Name: Cubane
Version: 1.0.11
Summary: Website/CMS/Shop and Backend Framework for Django.
Home-page: https://github.com/cubaneorg/cubane
Author: Cubane Organisation
Author-email: hello@cubane.org
License: GPL-3
Platform: UNKNOWN
Classifier: Development Status :: 5 - Production/Stable
Classifier: Intended Audience :: Developers
Classifier: License :: OSI Approved :: GNU General Public License v3 (GPLv3)
Classifier: Programming Language :: Python
Classifier: Programming Language :: Python :: 2
Classifier: Programming Language :: Python :: 2.7
Classifier: Topic :: Internet :: WWW/HTTP
Classifier: Topic :: Internet :: WWW/HTTP :: Dynamic Content
Classifier: Topic :: Internet :: WWW/HTTP :: Dynamic Content :: Content Management System
Classifier: Topic :: Internet :: WWW/HTTP :: Site Management
Classifier: Topic :: Software Development :: Libraries
Classifier: Topic :: Software Development :: Libraries :: Application Frameworks
Classifier: Topic :: Software Development :: Libraries :: Python Modules
Requires-Dist: Django (<=1.11,>=1.10)
Requires-Dist: psycopg2 (>=2.5.4)
Requires-Dist: beautifulsoup4 (>=4.5.3)
Requires-Dist: lxml (>=3.7.2)
Requires-Dist: django-htmlmin (>=0.9.0)
Requires-Dist: Wand (>=0.4.3)
Requires-Dist: requests (>=2.12.5)
Requires-Dist: requests[security]
Requires-Dist: pycrypto (>=2.6.1)
Requires-Dist: oauth2 (>=1.9.0.post1)
Requires-Dist: mailsnake (>=1.6.4)
Requires-Dist: ipaddr (>=2.1.11)
Requires-Dist: ifaddr (>=0.1.4)
Requires-Dist: pydns (>=2.3.6)
Requires-Dist: chardet (>=2.3.0)
Requires-Dist: stripe (>=1.46.0)
Requires-Dist: pyBarcode (>=0.7)
Requires-Dist: idna (>=2.5)
